{
  "services": [
    {
      "name": "GitHub API",
      "host": "api.github.com",
      "latency_ms": 24.5,
      "packet_loss": 0.0,
      "status": "ok",
      "history": [
        25.6,
        28.9,
        23.3,
        23.7,
        23.0,
        23.7,
        22.2,
        22.1,
        22.8,
        24.5
      ],
      "max_h": 28.9
    },
    {
      "name": "Cloudflare DNS",
      "host": "1.1.1.1",
      "latency_ms": 14.7,
      "packet_loss": 0.0,
      "status": "ok",
      "history": [
        14.2,
        14.2,
        15.8,
        14.3,
        15.1,
        16.1,
        14.8,
        14.8,
        15.2,
        14.7
      ],
      "max_h": 16.1
    },
    {
      "name": "Google DNS",
      "host": "8.8.8.8",
      "latency_ms": 17.2,
      "packet_loss": 0.0,
      "status": "ok",
      "history": [
        16.8,
        17.5,
        19.8,
        16.5,
        15.3,
        16.1,
        16.9,
        16.1,
        18.1,
        17.2
      ],
      "max_h": 19.8
    },
    {
      "name": "Gateway",
      "host": "192.168.0.1",
      "latency_ms": 2.1,
      "packet_loss": 0.0,
      "status": "ok",
      "history": [
        1.4,
        1.7,
        1.7,
        1.9,
        1.1,
        1.7,
        1.6,
        1.7,
        1.4,
        2.1
      ],
      "max_h": 2.1
    }
  ],
  "last_checked": "2026-07-04T16:35:01.516033+00:00",
  "services_ok": 4,
  "services_total": 4
}