{
  "services": [
    {
      "name": "GitHub API",
      "host": "api.github.com",
      "latency_ms": 27.4,
      "packet_loss": 0.0,
      "status": "ok",
      "history": [
        22.8,
        25.4,
        21.7,
        26.1,
        23.5,
        23.0,
        26.6,
        23.7,
        23.4,
        27.4
      ],
      "max_h": 27.4
    },
    {
      "name": "Cloudflare DNS",
      "host": "1.1.1.1",
      "latency_ms": 16.4,
      "packet_loss": 0.0,
      "status": "ok",
      "history": [
        14.8,
        16.7,
        20.1,
        14.9,
        14.6,
        15.2,
        13.9,
        14.8,
        15.4,
        16.4
      ],
      "max_h": 20.1
    },
    {
      "name": "Google DNS",
      "host": "8.8.8.8",
      "latency_ms": 18.0,
      "packet_loss": 0.0,
      "status": "ok",
      "history": [
        15.7,
        17.4,
        16.7,
        19.9,
        16.2,
        16.5,
        15.1,
        16.9,
        29.0,
        18.0
      ],
      "max_h": 29.0
    },
    {
      "name": "Gateway",
      "host": "192.168.0.1",
      "latency_ms": 1.2,
      "packet_loss": 0.0,
      "status": "ok",
      "history": [
        1.7,
        1.8,
        1.8,
        1.6,
        1.4,
        1.6,
        1.3,
        1.4,
        1.7,
        1.2
      ],
      "max_h": 1.8
    }
  ],
  "last_checked": "2026-07-06T20:35:01.948075+00:00",
  "services_ok": 4,
  "services_total": 4
}