{
  "services": [
    {
      "name": "GitHub API",
      "host": "api.github.com",
      "latency_ms": 24.6,
      "packet_loss": 0.0,
      "status": "ok",
      "history": [
        25.6,
        23.5,
        23.0,
        22.4,
        23.2,
        21.9,
        23.6,
        22.0,
        23.1,
        24.6
      ],
      "max_h": 25.6
    },
    {
      "name": "Cloudflare DNS",
      "host": "1.1.1.1",
      "latency_ms": 15.2,
      "packet_loss": 0.0,
      "status": "ok",
      "history": [
        14.1,
        15.2,
        12.8,
        15.9,
        14.9,
        14.2,
        17.5,
        15.2,
        14.5,
        15.2
      ],
      "max_h": 17.5
    },
    {
      "name": "Google DNS",
      "host": "8.8.8.8",
      "latency_ms": 16.4,
      "packet_loss": 0.0,
      "status": "ok",
      "history": [
        15.8,
        17.4,
        15.8,
        15.4,
        17.0,
        16.5,
        15.0,
        14.4,
        18.2,
        16.4
      ],
      "max_h": 18.2
    },
    {
      "name": "Gateway",
      "host": "192.168.0.1",
      "latency_ms": 1.7,
      "packet_loss": 0.0,
      "status": "ok",
      "history": [
        1.7,
        1.6,
        1.7,
        1.5,
        1.6,
        1.5,
        1.9,
        1.3,
        1.4,
        1.7
      ],
      "max_h": 1.9
    }
  ],
  "last_checked": "2026-06-27T03:35:01.194298+00:00",
  "services_ok": 4,
  "services_total": 4
}